{
    "songName": "",
    "positionInfo": [
        {
            "x": 578.2265625,
            "y": 428.07550048828127,
            "z": 0.0
        },
        {
            "x": 978.20703125,
            "y": 428.07550048828127,
            "z": 0.0
        },
        {
            "x": 1378.20703125,
            "y": 428.07550048828127,
            "z": 0.0
        },
        {
            "x": 1778.20703125,
            "y": 428.07550048828127,
            "z": 0.0
        },
        {
            "x": 2178.20703125,
            "y": 428.07550048828127,
            "z": 0.0
        },
        {
            "x": 2578.20703125,
            "y": 428.07550048828127,
            "z": 0.0
        },
        {
            "x": 2978.20703125,
            "y": 428.07550048828127,
            "z": 0.0
        },
        {
            "x": 3378.20703125,
            "y": 428.07550048828127,
            "z": 0.0
        },
        {
            "x": 3778.20703125,
            "y": 428.07550048828127,
            "z": 0.0
        },
        {
            "x": 4178.20703125,
            "y": 428.07550048828127,
            "z": 0.0
        },
        {
            "x": 4578.20703125,
            "y": 428.07550048828127,
            "z": 0.0
        },
        {
            "x": 4978.20703125,
            "y": 428.07550048828127,
            "z": 0.0
        },
        {
            "x": 5378.20703125,
            "y": 428.07550048828127,
            "z": 0.0
        },
        {
            "x": 5778.21484375,
            "y": 428.07550048828127,
            "z": 0.0
        },
        {
            "x": 6178.20703125,
            "y": 428.07550048828127,
            "z": 0.0
        },
        {
            "x": 6578.20703125,
            "y": 428.07550048828127,
            "z": 0.0
        },
        {
            "x": 6978.20703125,
            "y": 428.07550048828127,
            "z": 0.0
        },
        {
            "x": 7378.20703125,
            "y": 428.07550048828127,
            "z": 0.0
        },
        {
            "x": 7778.20703125,
            "y": 428.07550048828127,
            "z": 0.0
        },
        {
            "x": 8178.20703125,
            "y": 428.07550048828127,
            "z": 0.0
        },
        {
            "x": 7178.20703125,
            "y": 428.07550048828127,
            "z": 0.0
        },
        {
            "x": 7578.20703125,
            "y": 428.07550048828127,
            "z": 0.0
        },
        {
            "x": 7978.20703125,
            "y": 428.07550048828127,
            "z": 0.0
        },
        {
            "x": 8378.20703125,
            "y": 428.07550048828127,
            "z": 0.0
        },
        {
            "x": 8578.20703125,
            "y": 428.07550048828127,
            "z": 0.0
        },
        {
            "x": 8778.20703125,
            "y": 428.07550048828127,
            "z": 0.0
        },
        {
            "x": 8978.20703125,
            "y": 428.07550048828127,
            "z": 0.0
        },
        {
            "x": 9178.23046875,
            "y": 428.07550048828127,
            "z": 0.0
        },
        {
            "x": 9378.2109375,
            "y": 428.07550048828127,
            "z": 0.0
        },
        {
            "x": 9578.20703125,
            "y": 428.07550048828127,
            "z": 0.0
        },
        {
            "x": 9778.20703125,
            "y": 428.07550048828127,
            "z": 0.0
        },
        {
            "x": 9978.21484375,
            "y": 428.07550048828127,
            "z": 0.0
        },
        {
            "x": 10178.2109375,
            "y": 428.07550048828127,
            "z": 0.0
        },
        {
            "x": 10378.21484375,
            "y": 428.07550048828127,
            "z": 0.0
        },
        {
            "x": 10578.21484375,
            "y": 428.07550048828127,
            "z": 0.0
        },
        {
            "x": 10778.21875,
            "y": 428.07550048828127,
            "z": 0.0
        },
        {
            "x": 10978.21484375,
            "y": 428.07550048828127,
            "z": 0.0
        },
        {
            "x": 11178.20703125,
            "y": 428.07550048828127,
            "z": 0.0
        },
        {
            "x": 11378.20703125,
            "y": 428.07550048828127,
            "z": 0.0
        },
        {
            "x": 11578.20703125,
            "y": 428.07550048828127,
            "z": 0.0
        },
        {
            "x": 11778.20703125,
            "y": 428.07550048828127,
            "z": 0.0
        },
        {
            "x": 11978.20703125,
            "y": 428.07550048828127,
            "z": 0.0
        },
        {
            "x": 12178.20703125,
            "y": 428.07550048828127,
            "z": 0.0
        },
        {
            "x": 12378.20703125,
            "y": 428.07550048828127,
            "z": 0.0
        },
        {
            "x": 12578.20703125,
            "y": 428.07550048828127,
            "z": 0.0
        },
        {
            "x": 12778.20703125,
            "y": 428.07550048828127,
            "z": 0.0
        },
        {
            "x": 12978.20703125,
            "y": 428.07550048828127,
            "z": 0.0
        },
        {
            "x": 13178.20703125,
            "y": 428.07550048828127,
            "z": 0.0
        },
        {
            "x": 13378.20703125,
            "y": 428.07550048828127,
            "z": 0.0
        },
        {
            "x": 13578.20703125,
            "y": 428.07550048828127,
            "z": 0.0
        },
        {
            "x": 13778.20703125,
            "y": 428.07550048828127,
            "z": 0.0
        },
        {
            "x": 13978.20703125,
            "y": 428.07550048828127,
            "z": 0.0
        },
        {
            "x": 14178.20703125,
            "y": 428.07550048828127,
            "z": 0.0
        },
        {
            "x": 14378.20703125,
            "y": 428.07550048828127,
            "z": 0.0
        },
        {
            "x": 14578.20703125,
            "y": 428.07550048828127,
            "z": 0.0
        },
        {
            "x": 14778.20703125,
            "y": 428.07550048828127,
            "z": 0.0
        },
        {
            "x": 14978.20703125,
            "y": 428.07550048828127,
            "z": 0.0
        },
        {
            "x": 15178.20703125,
            "y": 428.07550048828127,
            "z": 0.0
        },
        {
            "x": 15378.20703125,
            "y": 428.07550048828127,
            "z": 0.0
        },
        {
            "x": 15578.20703125,
            "y": 428.07550048828127,
            "z": 0.0
        },
        {
            "x": 15778.20703125,
            "y": 428.07550048828127,
            "z": 0.0
        },
        {
            "x": 15978.20703125,
            "y": 428.07550048828127,
            "z": 0.0
        },
        {
            "x": 15878.20703125,
            "y": 428.07550048828127,
            "z": 0.0
        },
        {
            "x": 16078.20703125,
            "y": 428.07550048828127,
            "z": 0.0
        },
        {
            "x": 16278.20703125,
            "y": 428.07550048828127,
            "z": 0.0
        },
        {
            "x": 16378.20703125,
            "y": 428.07550048828127,
            "z": 0.0
        },
        {
            "x": 16478.20703125,
            "y": 428.07550048828127,
            "z": 0.0
        },
        {
            "x": 16578.20703125,
            "y": 428.07550048828127,
            "z": 0.0
        },
        {
            "x": 16778.20703125,
            "y": 428.07550048828127,
            "z": 0.0
        },
        {
            "x": 16978.20703125,
            "y": 428.07550048828127,
            "z": 0.0
        },
        {
            "x": 17178.20703125,
            "y": 428.07550048828127,
            "z": 0.0
        },
        {
            "x": 17378.142578125,
            "y": 428.07550048828127,
            "z": 0.0
        },
        {
            "x": 17578.1328125,
            "y": 428.07550048828127,
            "z": 0.0
        },
        {
            "x": 17778.162109375,
            "y": 428.07550048828127,
            "z": 0.0
        },
        {
            "x": 17978.1328125,
            "y": 428.07550048828127,
            "z": 0.0
        },
        {
            "x": 18178.19140625,
            "y": 428.07550048828127,
            "z": 0.0
        },
        {
            "x": 18378.19921875,
            "y": 428.07550048828127,
            "z": 0.0
        },
        {
            "x": 18578.193359375,
            "y": 428.07550048828127,
            "z": 0.0
        },
        {
            "x": 18778.2109375,
            "y": 428.07550048828127,
            "z": 0.0
        },
        {
            "x": 18978.1953125,
            "y": 428.07550048828127,
            "z": 0.0
        },
        {
            "x": 19078.173828125,
            "y": 428.07550048828127,
            "z": 0.0
        },
        {
            "x": 19178.173828125,
            "y": 428.07550048828127,
            "z": 0.0
        },
        {
            "x": 19278.18359375,
            "y": 428.07550048828127,
            "z": 0.0
        },
        {
            "x": 19478.18359375,
            "y": 428.07550048828127,
            "z": 0.0
        },
        {
            "x": 19578.1875,
            "y": 428.07550048828127,
            "z": 0.0
        },
        {
            "x": 19678.1875,
            "y": 428.07550048828127,
            "z": 0.0
        },
        {
            "x": 19778.177734375,
            "y": 428.07550048828127,
            "z": 0.0
        },
        {
            "x": 19878.1796875,
            "y": 428.07550048828127,
            "z": 0.0
        },
        {
            "x": 19978.201171875,
            "y": 428.07550048828127,
            "z": 0.0
        },
        {
            "x": 21178.1953125,
            "y": 428.07550048828127,
            "z": 0.0
        },
        {
            "x": 21278.19140625,
            "y": 428.07550048828127,
            "z": 0.0
        },
        {
            "x": 21378.203125,
            "y": 428.07550048828127,
            "z": 0.0
        },
        {
            "x": 21478.20703125,
            "y": 428.07550048828127,
            "z": 0.0
        },
        {
            "x": 21578.20703125,
            "y": 428.07550048828127,
            "z": 0.0
        },
        {
            "x": 21678.20703125,
            "y": 428.07550048828127,
            "z": 0.0
        },
        {
            "x": 21978.20703125,
            "y": 428.07550048828127,
            "z": 0.0
        },
        {
            "x": 22078.20703125,
            "y": 428.07550048828127,
            "z": 0.0
        },
        {
            "x": 22178.20703125,
            "y": 428.07550048828127,
            "z": 0.0
        },
        {
            "x": 22378.20703125,
            "y": 428.07550048828127,
            "z": 0.0
        },
        {
            "x": 22578.20703125,
            "y": 428.07550048828127,
            "z": 0.0
        },
        {
            "x": 22778.20703125,
            "y": 428.07550048828127,
            "z": 0.0
        },
        {
            "x": 22978.20703125,
            "y": 428.07550048828127,
            "z": 0.0
        },
        {
            "x": 23078.20703125,
            "y": 428.07550048828127,
            "z": 0.0
        },
        {
            "x": 23178.20703125,
            "y": 428.07550048828127,
            "z": 0.0
        },
        {
            "x": 23278.20703125,
            "y": 428.07550048828127,
            "z": 0.0
        },
        {
            "x": 24078.20703125,
            "y": 428.07550048828127,
            "z": 0.0
        },
        {
            "x": 24378.20703125,
            "y": 428.07550048828127,
            "z": 0.0
        },
        {
            "x": 24478.20703125,
            "y": 428.07550048828127,
            "z": 0.0
        },
        {
            "x": 24578.20703125,
            "y": 428.07550048828127,
            "z": 0.0
        },
        {
            "x": 24678.20703125,
            "y": 428.07550048828127,
            "z": 0.0
        },
        {
            "x": 24778.20703125,
            "y": 428.07550048828127,
            "z": 0.0
        },
        {
            "x": 24878.20703125,
            "y": 428.07550048828127,
            "z": 0.0
        },
        {
            "x": 25178.20703125,
            "y": 428.07550048828127,
            "z": 0.0
        },
        {
            "x": 25378.20703125,
            "y": 428.07550048828127,
            "z": 0.0
        },
        {
            "x": 20178.22265625,
            "y": 428.07550048828127,
            "z": 0.0
        },
        {
            "x": 20278.224609375,
            "y": 428.07550048828127,
            "z": 0.0
        },
        {
            "x": 20378.228515625,
            "y": 428.07550048828127,
            "z": 0.0
        },
        {
            "x": 20478.22265625,
            "y": 428.07550048828127,
            "z": 0.0
        },
        {
            "x": 20578.23046875,
            "y": 428.07550048828127,
            "z": 0.0
        },
        {
            "x": 20678.23046875,
            "y": 428.07550048828127,
            "z": 0.0
        },
        {
            "x": 20778.22265625,
            "y": 428.07550048828127,
            "z": 0.0
        },
        {
            "x": 25278.20703125,
            "y": 428.07550048828127,
            "z": 0.0
        },
        {
            "x": 25578.20703125,
            "y": 428.07550048828127,
            "z": 0.0
        },
        {
            "x": 25778.20703125,
            "y": 428.07550048828127,
            "z": 0.0
        },
        {
            "x": 25978.20703125,
            "y": 428.07550048828127,
            "z": 0.0
        },
        {
            "x": 26178.20703125,
            "y": 428.07550048828127,
            "z": 0.0
        },
        {
            "x": 26278.20703125,
            "y": 428.07550048828127,
            "z": 0.0
        },
        {
            "x": 26378.20703125,
            "y": 428.07550048828127,
            "z": 0.0
        },
        {
            "x": 26478.20703125,
            "y": 428.07550048828127,
            "z": 0.0
        },
        {
            "x": 26678.20703125,
            "y": 428.07550048828127,
            "z": 0.0
        },
        {
            "x": 26778.20703125,
            "y": 428.07550048828127,
            "z": 0.0
        },
        {
            "x": 26878.20703125,
            "y": 428.07550048828127,
            "z": 0.0
        },
        {
            "x": 26978.20703125,
            "y": 428.07550048828127,
            "z": 0.0
        },
        {
            "x": 27078.20703125,
            "y": 428.07550048828127,
            "z": 0.0
        },
        {
            "x": 27178.20703125,
            "y": 428.07550048828127,
            "z": 0.0
        },
        {
            "x": 23478.20703125,
            "y": 428.07550048828127,
            "z": 0.0
        },
        {
            "x": 23578.20703125,
            "y": 428.07550048828127,
            "z": 0.0
        },
        {
            "x": 23678.20703125,
            "y": 428.07550048828127,
            "z": 0.0
        },
        {
            "x": 23778.20703125,
            "y": 428.07550048828127,
            "z": 0.0
        },
        {
            "x": 23878.20703125,
            "y": 428.07550048828127,
            "z": 0.0
        },
        {
            "x": 23978.20703125,
            "y": 428.07550048828127,
            "z": 0.0
        },
        {
            "x": 27378.20703125,
            "y": 428.07550048828127,
            "z": 0.0
        },
        {
            "x": 27478.20703125,
            "y": 428.07550048828127,
            "z": 0.0
        },
        {
            "x": 27578.20703125,
            "y": 428.07550048828127,
            "z": 0.0
        },
        {
            "x": 27678.20703125,
            "y": 428.07550048828127,
            "z": 0.0
        },
        {
            "x": 27778.20703125,
            "y": 428.07550048828127,
            "z": 0.0
        },
        {
            "x": 27878.20703125,
            "y": 428.07550048828127,
            "z": 0.0
        },
        {
            "x": 28178.20703125,
            "y": 428.07550048828127,
            "z": 0.0
        },
        {
            "x": 28278.20703125,
            "y": 428.07550048828127,
            "z": 0.0
        },
        {
            "x": 28378.20703125,
            "y": 428.07550048828127,
            "z": 0.0
        },
        {
            "x": 28578.20703125,
            "y": 428.07550048828127,
            "z": 0.0
        },
        {
            "x": 28778.20703125,
            "y": 428.07550048828127,
            "z": 0.0
        },
        {
            "x": 28978.20703125,
            "y": 428.07550048828127,
            "z": 0.0
        },
        {
            "x": 29178.20703125,
            "y": 428.07550048828127,
            "z": 0.0
        },
        {
            "x": 29578.20703125,
            "y": 428.07550048828127,
            "z": 0.0
        },
        {
            "x": 29778.20703125,
            "y": 428.07550048828127,
            "z": 0.0
        },
        {
            "x": 29978.20703125,
            "y": 428.07550048828127,
            "z": 0.0
        },
        {
            "x": 30178.20703125,
            "y": 428.07550048828127,
            "z": 0.0
        },
        {
            "x": 30378.20703125,
            "y": 428.07550048828127,
            "z": 0.0
        },
        {
            "x": 30578.20703125,
            "y": 428.07550048828127,
            "z": 0.0
        },
        {
            "x": 30778.20703125,
            "y": 428.07550048828127,
            "z": 0.0
        },
        {
            "x": 30878.20703125,
            "y": 428.07550048828127,
            "z": 0.0
        },
        {
            "x": 30978.20703125,
            "y": 428.07550048828127,
            "z": 0.0
        },
        {
            "x": 31178.20703125,
            "y": 428.07550048828127,
            "z": 0.0
        },
        {
            "x": 31378.20703125,
            "y": 428.07550048828127,
            "z": 0.0
        },
        {
            "x": 31578.20703125,
            "y": 428.07550048828127,
            "z": 0.0
        },
        {
            "x": 31778.20703125,
            "y": 428.07550048828127,
            "z": 0.0
        },
        {
            "x": 31978.20703125,
            "y": 428.07550048828127,
            "z": 0.0
        },
        {
            "x": 32178.20703125,
            "y": 428.07550048828127,
            "z": 0.0
        },
        {
            "x": 32378.20703125,
            "y": 428.07550048828127,
            "z": 0.0
        },
        {
            "x": 32478.20703125,
            "y": 428.07550048828127,
            "z": 0.0
        },
        {
            "x": 32578.20703125,
            "y": 428.07550048828127,
            "z": 0.0
        },
        {
            "x": 32778.2109375,
            "y": 428.07550048828127,
            "z": 0.0
        },
        {
            "x": 32978.2109375,
            "y": 428.07550048828127,
            "z": 0.0
        },
        {
            "x": 33178.2109375,
            "y": 428.07550048828127,
            "z": 0.0
        },
        {
            "x": 33378.2109375,
            "y": 428.07550048828127,
            "z": 0.0
        },
        {
            "x": 33578.2109375,
            "y": 428.07550048828127,
            "z": 0.0
        },
        {
            "x": 34378.1953125,
            "y": 428.07550048828127,
            "z": 0.0
        },
        {
            "x": 34578.2109375,
            "y": 428.07550048828127,
            "z": 0.0
        },
        {
            "x": 34778.19921875,
            "y": 428.07550048828127,
            "z": 0.0
        },
        {
            "x": 34878.2109375,
            "y": 428.07550048828127,
            "z": 0.0
        },
        {
            "x": 35078.24609375,
            "y": 428.07550048828127,
            "z": 0.0
        },
        {
            "x": 35978.1875,
            "y": 428.07550048828127,
            "z": 0.0
        },
        {
            "x": 36178.2109375,
            "y": 428.07550048828127,
            "z": 0.0
        },
        {
            "x": 36378.21484375,
            "y": 428.07550048828127,
            "z": 0.0
        },
        {
            "x": 36578.26953125,
            "y": 428.07550048828127,
            "z": 0.0
        },
        {
            "x": 37578.2265625,
            "y": 428.07550048828127,
            "z": 0.0
        },
        {
            "x": 37978.20703125,
            "y": 428.07550048828127,
            "z": 0.0
        },
        {
            "x": 38178.1953125,
            "y": 428.07550048828127,
            "z": 0.0
        },
        {
            "x": 38278.2265625,
            "y": 428.07550048828127,
            "z": 0.0
        },
        {
            "x": 38478.1953125,
            "y": 428.07550048828127,
            "z": 0.0
        },
        {
            "x": 38978.21875,
            "y": 428.07550048828127,
            "z": 0.0
        },
        {
            "x": 39178.20703125,
            "y": 428.07550048828127,
            "z": 0.0
        },
        {
            "x": 39378.2109375,
            "y": 428.07550048828127,
            "z": 0.0
        },
        {
            "x": 39578.203125,
            "y": 428.07550048828127,
            "z": 0.0
        },
        {
            "x": 39778.1953125,
            "y": 428.07550048828127,
            "z": 0.0
        },
        {
            "x": 39978.1953125,
            "y": 428.07550048828127,
            "z": 0.0
        },
        {
            "x": 40078.1953125,
            "y": 428.07550048828127,
            "z": 0.0
        },
        {
            "x": 40178.19140625,
            "y": 428.07550048828127,
            "z": 0.0
        },
        {
            "x": 40378.19140625,
            "y": 428.07550048828127,
            "z": 0.0
        },
        {
            "x": 40578.2109375,
            "y": 428.07550048828127,
            "z": 0.0
        },
        {
            "x": 40778.1953125,
            "y": 428.07550048828127,
            "z": 0.0
        },
        {
            "x": 40978.20703125,
            "y": 428.07550048828127,
            "z": 0.0
        },
        {
            "x": 41178.21875,
            "y": 428.07550048828127,
            "z": 0.0
        },
        {
            "x": 41378.2109375,
            "y": 428.07550048828127,
            "z": 0.0
        },
        {
            "x": 41478.1953125,
            "y": 428.07550048828127,
            "z": 0.0
        },
        {
            "x": 41578.203125,
            "y": 428.07550048828127,
            "z": 0.0
        },
        {
            "x": 41778.1953125,
            "y": 428.07550048828127,
            "z": 0.0
        },
        {
            "x": 41978.203125,
            "y": 428.07550048828127,
            "z": 0.0
        },
        {
            "x": 42178.203125,
            "y": 428.07550048828127,
            "z": 0.0
        },
        {
            "x": 42378.203125,
            "y": 428.07550048828127,
            "z": 0.0
        },
        {
            "x": 42578.203125,
            "y": 428.07550048828127,
            "z": 0.0
        },
        {
            "x": 42778.203125,
            "y": 428.07550048828127,
            "z": 0.0
        },
        {
            "x": 42878.203125,
            "y": 428.07550048828127,
            "z": 0.0
        },
        {
            "x": 42978.203125,
            "y": 428.07550048828127,
            "z": 0.0
        },
        {
            "x": 43178.203125,
            "y": 428.07550048828127,
            "z": 0.0
        },
        {
            "x": 43378.203125,
            "y": 428.07550048828127,
            "z": 0.0
        },
        {
            "x": 43578.203125,
            "y": 428.07550048828127,
            "z": 0.0
        },
        {
            "x": 43778.203125,
            "y": 428.07550048828127,
            "z": 0.0
        },
        {
            "x": 43978.203125,
            "y": 428.07550048828127,
            "z": 0.0
        },
        {
            "x": 44178.203125,
            "y": 428.07550048828127,
            "z": 0.0
        },
        {
            "x": 44378.203125,
            "y": 428.07550048828127,
            "z": 0.0
        },
        {
            "x": 44478.203125,
            "y": 428.07550048828127,
            "z": 0.0
        },
        {
            "x": 44578.20703125,
            "y": 428.07550048828127,
            "z": 0.0
        },
        {
            "x": 44978.20703125,
            "y": 428.07550048828127,
            "z": 0.0
        },
        {
            "x": 45378.20703125,
            "y": 428.07550048828127,
            "z": 0.0
        }
    ],
    "spikePositionInfo": [],
    "longNotePositionInfo": [
        {
            "x": 44678.20703125,
            "y": 428.07550048828127,
            "z": 0.0
        },
        {
            "x": 45078.20703125,
            "y": 428.07550048828127,
            "z": 0.0
        },
        {
            "x": 45478.20703125,
            "y": 428.07550048828127,
            "z": 0.0
        }
    ],
    "longNoteEndPositionInfo": [
        {
            "x": 44778.20703125,
            "y": 428.07550048828127,
            "z": 0.0
        },
        {
            "x": 45178.20703125,
            "y": 428.07550048828127,
            "z": 0.0
        },
        {
            "x": 45578.20703125,
            "y": 428.07550048828127,
            "z": 0.0
        }
    ],
    "longWidthInfo": [
        800.0,
        200.0,
        218.181884765625
    ]
}